undict/__init__.py
undict/undict.py
undict-0.1.0.dist-info/DESCRIPTION.rst
undict-0.1.0.dist-info/METADATA
undict-0.1.0.dist-info/RECORD
undict-0.1.0.dist-info/WHEEL
undict-0.1.0.dist-info/metadata.json
undict-0.1.0.dist-info/top_level.txt
