Metadata-Version: 2.0
Name: undict
Version: 0.1.0
Summary: Undict - Easier API for using Dictionary, especially with json
Home-page: https://github.com/firstprayer/undict.git
Author: firstprayer
Author-email: zhangty10@gmail.com
License: UNKNOWN
Platform: UNKNOWN
